pyhdmap/__init__.py
pyhdmap/api/hdmap.py
pyhdmap/config/config.py
pyhdmap/config/service.yaml
pyhdmap/config/hdmap_lib_conf/hdmap_lib.conf
pyhdmap/config/hdmap_lib_conf/city/road_manager_config.pb.txt
pyhdmap/config/hdmap_lib_conf/port_lvsi/road_manager_config.pb.txt
pyhdmap/config/hdmap_lib_conf/port_meishan/road_link_config.pb.txt
pyhdmap/config/hdmap_lib_conf/port_meishan/road_manager_config.pb.txt
pyhdmap/config/hdmap_lib_conf/port_meishan/cubic_reference_line/1_20_4.pb.txt
pyhdmap/config/hdmap_lib_conf/port_meishan/cubic_reference_line/2_20_4.pb.txt
pyhdmap/config/hdmap_lib_conf/port_meishan/cubic_reference_line/3_20_4.pb.txt
pyhdmap/config/hdmap_lib_conf/port_meishan/cubic_reference_line/4_20_4.pb.txt
pyhdmap/config/hdmap_lib_conf/port_meishan/cubic_reference_line/8_20_3.pb.txt
pyhdmap/config/hdmap_lib_conf/port_meishan/cubic_reference_line/8_3_7.pb.txt
pyhdmap/config/hdmap_lib_conf/port_meishan/cubic_reference_line/9_20_4.pb.txt
pyhdmap/config/hdmap_lib_conf/port_meishan_driverless/road_link_config.pb.txt
pyhdmap/config/hdmap_lib_conf/port_meishan_driverless/road_manager_config.pb.txt
pyhdmap/config/hdmap_lib_conf/port_meishan_driverless/cubic_reference_line/20_2_3.pb.txt
pyhdmap/config/hdmap_lib_conf/port_meishan_driverless/cubic_reference_line/20_3_3.pb.txt
pyhdmap/config/hdmap_lib_conf/port_meishan_driverless/cubic_reference_line/20_8_3.pb.txt
pyhdmap/config/hdmap_lib_conf/port_meishan_driverless/cubic_reference_line/20_8_4.pb.txt
pyhdmap/config/hdmap_lib_conf/port_meishan_driverless/cubic_reference_line/2_20_4.pb.txt
pyhdmap/config/hdmap_lib_conf/port_meishan_driverless/cubic_reference_line/2_8_7.pb.txt
pyhdmap/config/hdmap_lib_conf/port_meishan_driverless/cubic_reference_line/2_8_8.pb.txt
pyhdmap/config/hdmap_lib_conf/port_meishan_driverless/cubic_reference_line/3_20_4.pb.txt
pyhdmap/config/hdmap_lib_conf/port_meishan_driverless/cubic_reference_line/3_8_7.pb.txt
pyhdmap/config/hdmap_lib_conf/port_meishan_driverless/cubic_reference_line/3_8_8.pb.txt
fabu_pyhdmap-0.0.7.dist-info/LICENSE
fabu_pyhdmap-0.0.7.dist-info/METADATA
fabu_pyhdmap-0.0.7.dist-info/WHEEL
fabu_pyhdmap-0.0.7.dist-info/top_level.txt
fabu_pyhdmap-0.0.7.dist-info/RECORD
