Metadata-Version: 2.1
Name: fabu-pyhdmap
Version: 0.0.7
Summary: UNKNOWN
Home-page: http://git.fabu.ai/zhangqiuyang/hdmapsdk-python
Author: zhangqiuyang
Author-email: zhangqiuyang@fabu.ai
License: Apache
Platform: UNKNOWN
Requires-Python: >=3.7
